firdawslab3/__init__.py
firdawslab3/firdawslab3.py
firdawslab3-1.0.0.dist-info/LICENSE.txt
firdawslab3-1.0.0.dist-info/METADATA
firdawslab3-1.0.0.dist-info/WHEEL
firdawslab3-1.0.0.dist-info/top_level.txt
firdawslab3-1.0.0.dist-info/RECORD
