Metadata-Version: 2.1
Name: firdawslab3
Version: 1.0.0
Summary: An awesome package that does something
Home-page: http://pypi.python.org/pypi/firdawslab3/
Author: firdaws
Author-email: firdawsbenahmed20@gmail.com
License: LICENSE.txt
License-File: LICENSE.txt
Requires-Dist: firdawslab3
